excellentman.py
excellentman-1.5.0.dist-info/METADATA
excellentman-1.5.0.dist-info/WHEEL
excellentman-1.5.0.dist-info/entry_points.txt
excellentman-1.5.0.dist-info/top_level.txt
excellentman-1.5.0.dist-info/RECORD
