Metadata-Version: 2.1
Name: excellentman
Version: 1.5.0
Summary: A tool for running Newman with parameters from an Excel file
Author: Alec and Lindsay
Classifier: Programming Language :: Python :: 3
Classifier: License :: OSI Approved :: MIT License
Classifier: Operating System :: OS Independent
Requires-Python: >=3.8
Requires-Dist: openpyxl
